transcribe_cli/__init__.py
transcribe_cli/audio_providers/__init__.py
transcribe_cli/audio_providers/audio_provider.py
transcribe_cli/audio_providers/youtube_audio_provider.py
transcribe_cli/downloader.py
transcribe_cli/main.py
transcribe_cli/transcriber.py
transcribe_cli-0.1.4.dist-info/METADATA
transcribe_cli-0.1.4.dist-info/WHEEL
transcribe_cli-0.1.4.dist-info/entry_points.txt
transcribe_cli-0.1.4.dist-info/RECORD
