Metadata-Version: 2.1
Name: transcribe-cli
Version: 0.1.4
Summary: 
Author: Andrei Chenchik
Author-email: andrei@chenchik.me
Requires-Python: >=3.12,<4.0
Classifier: Programming Language :: Python :: 3
Classifier: Programming Language :: Python :: 3.12
Requires-Dist: assemblyai (>=0.33.0,<0.34.0)
Requires-Dist: python-dotenv (>=1.0.1,<2.0.0)
Requires-Dist: yt-dlp (>=2024.8.6,<2025.0.0)
